factuality/__init__.py
factuality/__main__.py
factuality/claim_splitter/.gitkeep
factuality/claim_splitter/__init_.py
factuality/claim_splitter/claim_splitter.py
factuality/fact_check/__init__.py
factuality/fact_check/fact_check.py
factuality/final_conclusion/__init__.py
factuality/final_conclusion/final_conclusion.py
factuality/result_output/.gitkeep
factuality/result_output/__init__.py
factuality/result_output/markdown.py
factuality/runner/__init__.py
factuality/runner/factuality.py
factuality/search/.gitkeep
factuality/search/__init__.py
factuality/search/bing/__init__.py
factuality/search/bing/bing_search.py
factuality/search/google/.gitkeep
factuality/search/google/__init__.py
factuality/search/google/google_search.py
factuality/search/search.py
factuality/utils/__init__.py
factuality/utils/defaults.py
factuality/utils/logging.py
factuality/utils/options.py
factuality-1.0.14.dist-info/LICENSE
factuality-1.0.14.dist-info/METADATA
factuality-1.0.14.dist-info/WHEEL
factuality-1.0.14.dist-info/entry_points.txt
factuality-1.0.14.dist-info/RECORD
