Metadata-Version: 2.1
Name: factuality
Version: 1.0.14
Summary: 
License: MIT
Author: Felix Mönckemeyer
Author-email: felix.moenckemeyer@rwth-aachen.de
Requires-Python: >=3.11,<4.0
Classifier: License :: OSI Approved :: MIT License
Classifier: Programming Language :: Python :: 3
Classifier: Programming Language :: Python :: 3.11
Classifier: Programming Language :: Python :: 3.12
Requires-Dist: gpt-json (>=0.4.2,<0.5.0)
Requires-Dist: newspaper3k (>=0.2.8,<0.3.0)
Requires-Dist: pytablewriter (>=1.2.0,<2.0.0)
Requires-Dist: python-dotenv (>=1.0.1,<2.0.0)
Requires-Dist: rich (>=13.7.1,<14.0.0)
Requires-Dist: structlog (>=24.1.0,<25.0.0)
